{
  "object" : {
    "artifacts" : [

    ],
    "dependencies" : [
      {
        "basedOn" : null,
        "packageRef" : {
          "identity" : "perfect-crud",
          "kind" : "remoteSourceControl",
          "location" : "https://github.com/PerfectlySoft/Perfect-CRUD.git",
          "name" : "PerfectCRUD"
        },
        "state" : {
          "checkoutState" : {
            "revision" : "5a947634b7ce0b991e8f455a61ce02449f2e6f36",
            "version" : "1.2.3"
          },
          "name" : "sourceControlCheckout"
        },
        "subpath" : "Perfect-CRUD"
      },
      {
        "basedOn" : null,
        "packageRef" : {
          "identity" : "perfect-mysql",
          "kind" : "remoteSourceControl",
          "location" : "https://github.com/PerfectlySoft/Perfect-MySQL.git",
          "name" : "PerfectMySQL"
        },
        "state" : {
          "checkoutState" : {
            "revision" : "fe63085fe4639944657bf2f33b775e8036974eef",
            "version" : "3.5.1"
          },
          "name" : "sourceControlCheckout"
        },
        "subpath" : "Perfect-MySQL"
      },
      {
        "basedOn" : null,
        "packageRef" : {
          "identity" : "perfect-mysqlclient",
          "kind" : "remoteSourceControl",
          "location" : "https://github.com/PerfectlySoft/Perfect-mysqlclient.git",
          "name" : "mysqlclient"
        },
        "state" : {
          "checkoutState" : {
            "revision" : "ed4f0e775c874b535fb24b00e6600b81f2932907",
            "version" : "2.1.1"
          },
          "name" : "sourceControlCheckout"
        },
        "subpath" : "Perfect-mysqlclient"
      }
    ]
  },
  "version" : 6
}